aplp_lib.cp311-win_amd64.pyd
wave_runtime.cp311-win_amd64.pyd
wave_lang/__init__.py
wave_lang/aot/__init__.py
wave_lang/aot/compiled_module.py
wave_lang/aot/decompositions.py
wave_lang/aot/exporter.py
wave_lang/aot/fx_programs.py
wave_lang/aot/params.py
wave_lang/aot/tensor_traits.py
wave_lang/aot/builtins/__init__.py
wave_lang/aot/builtins/globals.py
wave_lang/aot/builtins/jittable.py
wave_lang/aot/passes/__init__.py
wave_lang/aot/passes/functorch.py
wave_lang/aot/support/ir_utils.py
wave_lang/aot/support/procedural/__init__.py
wave_lang/aot/support/procedural/base.py
wave_lang/aot/support/procedural/exported_program.py
wave_lang/aot/support/procedural/globals.py
wave_lang/aot/support/procedural/iree_emitter.py
wave_lang/aot/support/procedural/primitives.py
wave_lang/aot/support/procedural/tracer.py
wave_lang/debugging/html_viewer.py
wave_lang/dynamo/__init__.py
wave_lang/dynamo/decompositions.py
wave_lang/dynamo/type_conversion.py
wave_lang/kernel/__init__.py
wave_lang/kernel/_support/context.py
wave_lang/kernel/_support/dtype.py
wave_lang/kernel/_support/indexing.py
wave_lang/kernel/_support/location.py
wave_lang/kernel/_support/regions.py
wave_lang/kernel/_support/shaped_type.py
wave_lang/kernel/_support/tracing.py
wave_lang/kernel/compiler/base.py
wave_lang/kernel/compiler/builder.py
wave_lang/kernel/compiler/debug_attrs.py
wave_lang/kernel/compiler/dispatch_codegen.py
wave_lang/kernel/compiler/host_codegen.py
wave_lang/kernel/compiler/host_utils.py
wave_lang/kernel/compiler/kernel_codegen.py
wave_lang/kernel/compiler/op_matchers.py
wave_lang/kernel/compiler/utils.py
wave_lang/kernel/lang/__init__.py
wave_lang/kernel/lang/global_symbols.py
wave_lang/kernel/lang/grid.py
wave_lang/kernel/lang/kernel_buffer.py
wave_lang/kernel/lang/prims.py
wave_lang/kernel/lang/types.py
wave_lang/kernel/lang/wave_types.py
wave_lang/kernel/ops/__init__.py
wave_lang/kernel/ops/base.py
wave_lang/kernel/ops/control_flow.py
wave_lang/kernel/ops/core.py
wave_lang/kernel/ops/math.py
wave_lang-3.8.2.dist-info/licenses/LICENSE
wave_lang-3.8.2.dist-info/METADATA
wave_lang-3.8.2.dist-info/WHEEL
wave_lang-3.8.2.dist-info/top_level.txt
wave_lang-3.8.2.dist-info/RECORD
