Metadata-Version: 2.4
Name: wave-lang
Version: 3.8.2
Summary: Wave Language for Machine Learning
Author: IREE Authors
Author-email: iree-technical-discussion@lists.lfaidata.foundation
License: Apache-2.0
Project-URL: homepage, https://iree.dev/
Project-URL: repository, https://github.com/iree-org/wave/
Project-URL: documentation, https://wave.readthedocs.io/en/latest/
Classifier: Development Status :: 5 - Production/Stable
Classifier: License :: OSI Approved :: Apache Software License
Classifier: Programming Language :: Python :: 3
License-File: LICENSE
Requires-Dist: numpy
Requires-Dist: iree-base-compiler==3.8.0
Requires-Dist: iree-base-runtime==3.8.0
Requires-Dist: Jinja2
Requires-Dist: ml_dtypes
Requires-Dist: typing_extensions
Provides-Extra: testing
Requires-Dist: pytest; extra == "testing"
Requires-Dist: pytest-xdist; extra == "testing"
Dynamic: author
Dynamic: author-email
Dynamic: classifier
Dynamic: description
Dynamic: description-content-type
Dynamic: license
Dynamic: license-file
Dynamic: project-url
Dynamic: provides-extra
Dynamic: requires-dist
Dynamic: summary
